nr/__init__.py
nr/utils/__init__.py
nr/utils/flask/__init__.py
nr/utils/flask/tasks.py
nr/utils/flask/wsgi.py
nr.utils.flask-0.2.1.dist-info/METADATA
nr.utils.flask-0.2.1.dist-info/WHEEL
nr.utils.flask-0.2.1.dist-info/top_level.txt
nr.utils.flask-0.2.1.dist-info/RECORD
