Metadata-Version: 2.1
Name: nr.utils.flask
Version: 0.2.1
Summary: Package description here.
Home-page: https://git.niklasrosenstein.com/NiklasRosenstein/nr-python-libs
Author: Niklas Rosenstein
Author-email: rosensteinniklas@gmail.com
License: MIT
Platform: UNKNOWN
